vector_quantize_tf/__init__.py
vector_quantize_tf/vector_quantize_tf.py
vector_quantize_tf-0.0.9.dist-info/LICENSE
vector_quantize_tf-0.0.9.dist-info/METADATA
vector_quantize_tf-0.0.9.dist-info/WHEEL
vector_quantize_tf-0.0.9.dist-info/top_level.txt
vector_quantize_tf-0.0.9.dist-info/RECORD
