Metadata-Version: 2.1
Name: vector-quantize-tf
Version: 0.0.9
Summary: tensorflowでの残差ベクトル量子化の実装
Author: anime-song
License: MIT license
License-File: LICENSE
Requires-Dist: tensorflow
Requires-Dist: scikit-learn
